commit_generation_datasets/__init__.py
commit_generation_datasets/datasets.py
commit_generation_datasets-0.0.8.dist-info/LICENSE
commit_generation_datasets-0.0.8.dist-info/METADATA
commit_generation_datasets-0.0.8.dist-info/WHEEL
commit_generation_datasets-0.0.8.dist-info/top_level.txt
commit_generation_datasets-0.0.8.dist-info/RECORD
