Metadata-Version: 2.1
Name: commit-generation-datasets
Version: 0.0.8
Summary: Dataset downloader for the commits generation project
Home-page: https://github.com/commits-generation/commit-generation-datasets
Author: Wassim Benzarti
Author-email: m.wassim.benzarti@gmail.com
License: UNKNOWN
Platform: UNKNOWN
Classifier: Programming Language :: Python :: 3
Classifier: License :: OSI Approved :: MIT License
Classifier: Operating System :: OS Independent
Requires-Python: >=3.6
